{
    "version": "633",
    "description": "A terminal pager program used to view (but not change) the contents of a text file one screen at a time, similar to the 'more' command.",
    "homepage": "https://www.greenwoodsoftware.com/less/",
    "license": "GPL-3.0-only|BSD-3-Clause",
    "architecture": {
        "64bit": {
            "url": "https://github.com/jftuga/less-Windows/releases/download/less-v633/less-x64.zip",
            "hash": "3dd5d3cbd203def8c8e5247d3180b0b233ee213930b4f1f8f30ebc49a731078c"
        }
    },
    "bin": [
        "less.exe",
        "lesskey.exe"
    ],
    "checkver": {
        "github": "https://github.com/jftuga/less-Windows",
        "regex": "tag/less-v([\\d.]+)"
    },
    "autoupdate": {
        "architecture": {
            "64bit": {
                "url": "https://github.com/jftuga/less-Windows/releases/download/less-v$version/less-x64.zip"
            }
        }
    }
}
